{
  "current_price": 210.57,
  "ma50": 215.43,
  "ma200": 224.58,
  "high_52w": 254.0,
  "low_52w": 167.32,
  "avg_vol_20d": 45457689,
  "current_vol": 43846286,
  "change_3mo_pct": -12.6,
  "ma20": 209.83,
  "rsi14": 50.95,
  "macd": -2.244,
  "macd_signal": -2.454,
  "bb_upper": 219.02,
  "bb_lower": 200.63,
  "bb_pct": 0.54,
  "atr14": 5.59,
  "vol_ratio": 0.96,
  "trend_status": "DOWNTREND",
  "tech_score": 48.0,
  "var_95": -3.05,
  "sharpe": 0.24,
  "sortino": 0.35,
  "beta": 1.42,
  "risk_score": 35.0,
  "_cached_at": "2026-04-02T07:54:23.256493"
}