{
  "current_price": 387.39,
  "ma50": 353.71,
  "ma200": 326.32,
  "high_52w": 416.39,
  "low_52w": 265.66,
  "avg_vol_20d": 2695470,
  "current_vol": 7091800,
  "change_3mo_pct": 37.67,
  "ma20": 388.07,
  "rsi14": 54.48,
  "macd": 9.88,
  "macd_signal": 12.74,
  "bb_upper": 418.52,
  "bb_lower": 357.62,
  "bb_pct": 0.49,
  "atr14": 19.51,
  "vol_ratio": 2.63,
  "trend_status": "UPTREND",
  "tech_score": 75.0,
  "var_95": -3.24,
  "sortino": 1.18,
  "max_drawdown": 28.8,
  "beta": 1.15,
  "calmar": 1.21,
  "risk_score": 65.0,
  "_cached_at": "2026-06-19T06:16:42.830315"
}