{
  "current_price": 9.53,
  "ma50": 10.25,
  "ma200": 16.7,
  "high_52w": 31.3,
  "low_52w": 9.15,
  "avg_vol_20d": 5825005,
  "current_vol": 4401200,
  "change_3mo_pct": -18.48,
  "ma20": 10.04,
  "rsi14": 38.1,
  "macd": -0.174,
  "macd_signal": -0.104,
  "bb_upper": 10.84,
  "bb_lower": 9.24,
  "bb_pct": 0.18,
  "atr14": 0.56,
  "vol_ratio": 0.76,
  "trend_status": "DOWNTREND",
  "tech_score": 19.0,
  "var_95": -7.26,
  "sharpe": -0.99,
  "sortino": -1.98,
  "beta": 1.19,
  "risk_score": 15.0,
  "_cached_at": "2026-04-01T04:06:50.305984"
}