{
  "articles": [
    {
      "title": "Tom Lee's Small-Cap Granny Shots ETF Reloads: First Solar, Zoom Among 10 New Buys — Tom Lee&#39;s GRNJ added First Solar, Zoom and eight other stocks in its latest rebalance as assets under management cli",
      "link": "https://finnhub.io/api/news?id=e9e1311b6f32abd5ac72f1ed3c6114c41ff04d69d37902a23c11c2dee769d339",
      "publisher": "Benzinga",
      "date": "2026-06-10 16:44",
      "_source": "finnhub",
      "_score": 14.4,
      "symbol": "FSLR"
    },
    {
      "title": "Array, Nextpower, and First Solar Shares Are Falling, What You Need To Know — A number of stocks fell in the afternoon session after early gains reversed and a midday helicopter incident introduced ",
      "link": "https://finnhub.io/api/news?id=920661d4b984b95eabf2c06007b553feb59038ac35e93d851b5c25645e596373",
      "publisher": "Yahoo",
      "date": "2026-06-10 01:02",
      "_source": "finnhub",
      "_score": 12.96,
      "symbol": "FSLR"
    },
    {
      "title": "If You Invested $1000 In First Solar Stock 10 Years Ago, You Would Have This Much Today —  ",
      "link": "https://finnhub.io/api/news?id=21fae2499dd2044924054a34c884af407412183b49f67480e897bf6cdc495db0",
      "publisher": "Benzinga",
      "date": "2026-06-09 19:00",
      "_source": "finnhub",
      "_score": 12.96,
      "symbol": "FSLR"
    },
    {
      "title": "Stock Of The Day: Is This The Bottom For First Solar? — First Solar shares are trading at an important price level. There is a good chance that the support will break and head ",
      "link": "https://finnhub.io/api/news?id=eed523b496f3e82419bda4ecd4e179bf61c65f93aad5097ae8f8a363370edfb4",
      "publisher": "Benzinga",
      "date": "2026-06-09 11:40",
      "_source": "finnhub",
      "_score": 12.96,
      "symbol": "FSLR"
    },
    {
      "title": "First Solar (FSLR) Is Down 7.9% After Section 45X Windfall Meets Policy And Insider Uncertainty – Has The Bull Case Changed? — In recent days, First Solar reported guidance incorporating an estimated US$2.10 billion to US$2.19 billion in Section 4",
      "link": "https://finnhub.io/api/news?id=12ae381c18a4a20d2e114eca260ce7a8621d14b77274c1ed32e4e6a96d98e4e3",
      "publisher": "Yahoo",
      "date": "2026-06-08 16:10",
      "_source": "finnhub",
      "_score": 12.8,
      "symbol": "FSLR"
    },
    {
      "title": "First Solar (FSLR) Dips More Than Broader Market: What You Should Know — The latest trading day saw First Solar (FSLR) settling at $279.01, representing a -11.41% change from its previous close",
      "link": "https://finnhub.io/api/news?id=99c43eb11dd0a8d797df38f233085530241a82f6dd615c736274c5883f0da7bc",
      "publisher": "Yahoo",
      "date": "2026-06-05 21:45",
      "_source": "finnhub",
      "_score": 8.0,
      "symbol": "FSLR"
    },
    {
      "title": "First Solar: Tax Credits To Provide Short-Term Boost In Margins (Rating Downgrade) — First Solar expands margins via Section 45x credits but faces geographic concentration and long-term tariff risks. Read ",
      "link": "https://finnhub.io/api/news?id=6e687f6db3d9a71c5c7ebebeb30dd2e133668d2fdf05dd073b439b3d03985f67",
      "publisher": "SeekingAlpha",
      "date": "2026-06-05 09:59",
      "_source": "finnhub",
      "_score": 3.6,
      "symbol": "FSLR"
    },
    {
      "title": "Here is What to Know Beyond Why First Solar, Inc. (FSLR) is a Trending Stock",
      "link": "https://finance.yahoo.com/markets/stocks/articles/know-beyond-why-first-solar-130005972.html",
      "publisher": "Zacks",
      "date": "2026-06-03T13:00:05Z",
      "_source": "yfinance",
      "_score": 3.599999999999999,
      "symbol": "FSLR"
    },
    {
      "title": "Selling US$8.5m Of First Solar Stock Rewarded Insiders",
      "link": "https://finance.yahoo.com/markets/stocks/articles/selling-us-8-5m-first-110015123.html",
      "publisher": "Simply Wall St.",
      "date": "2026-06-03T11:00:15Z",
      "_source": "yfinance",
      "_score": 1.6199999999999997,
      "symbol": "FSLR"
    }
  ],
  "_cached_at": "2026-06-11T05:30:51.228599"
}