{
  "current_price": 235.87,
  "ma50": 240.42,
  "ma200": 280.94,
  "high_52w": 326.79,
  "low_52w": 218.45,
  "avg_vol_20d": 1877027,
  "current_vol": 1233952,
  "change_3mo_pct": -2.04,
  "ma20": 236.33,
  "rsi14": 58.56,
  "macd": -1.168,
  "macd_signal": -1.349,
  "bb_upper": 250.99,
  "bb_lower": 221.67,
  "bb_pct": 0.48,
  "atr14": 8.64,
  "vol_ratio": 0.66,
  "trend_status": "DOWNTREND",
  "tech_score": 48.0,
  "var_95": -3.58,
  "sortino": -0.65,
  "max_drawdown": 33.2,
  "beta": 1.43,
  "calmar": -0.32,
  "risk_score": 38.0,
  "_cached_at": "2026-04-30T03:38:05.260404"
}