{
  "current_price": 648.84,
  "ma50": 712.38,
  "ma200": 548.74,
  "high_52w": 785.12,
  "low_52w": 372.18,
  "avg_vol_20d": 1441765,
  "current_vol": 868700,
  "change_3mo_pct": 7.27,
  "ma20": 688.03,
  "rsi14": 37.6,
  "macd": -13.965,
  "macd_signal": -9.455,
  "bb_upper": 744.03,
  "bb_lower": 632.03,
  "bb_pct": 0.15,
  "atr14": 27.16,
  "vol_ratio": 0.6,
  "trend_status": "BREAKDOWN",
  "tech_score": 22.0,
  "var_95": -3.94,
  "sortino": 2.18,
  "max_drawdown": 17.6,
  "beta": 1.22,
  "calmar": 3.35,
  "risk_score": 81.0,
  "_cached_at": "2026-07-16T04:00:01.245402"
}