{
  "current_price": 283.78,
  "ma50": 291.41,
  "ma200": 269.08,
  "high_52w": 315.2,
  "low_52w": 200.29,
  "avg_vol_20d": 66979390,
  "current_vol": 261693600,
  "change_3mo_pct": 11.11,
  "ma20": 298.29,
  "rsi14": 33.48,
  "macd": -2.237,
  "macd_signal": 0.534,
  "bb_upper": 318.33,
  "bb_lower": 278.25,
  "bb_pct": 0.14,
  "atr14": 9.22,
  "vol_ratio": 3.91,
  "trend_status": "CONSOLIDATION",
  "tech_score": 38.0,
  "var_95": -1.96,
  "sortino": 2.05,
  "max_drawdown": 13.8,
  "beta": 1.09,
  "calmar": 2.75,
  "risk_score": 100.0,
  "_cached_at": "2026-06-29T05:29:21.964471"
}