{
  "current_price": 1948.69,
  "ma50": 1871.5,
  "ma200": 1289.79,
  "high_52w": 2066.51,
  "low_52w": 520.49,
  "avg_vol_20d": 544310,
  "current_vol": 593700,
  "change_3mo_pct": 37.56,
  "ma20": 1895.93,
  "rsi14": 54.47,
  "macd": 29.98,
  "macd_signal": 29.764,
  "bb_upper": 2054.31,
  "bb_lower": 1737.55,
  "bb_pct": 0.67,
  "atr14": 114.58,
  "vol_ratio": 1.09,
  "trend_status": "UPTREND",
  "tech_score": 92.0,
  "var_95": -5.66,
  "sortino": 4.14,
  "max_drawdown": 15.8,
  "beta": 1.67,
  "calmar": 9.24,
  "risk_score": 68.0,
  "_cached_at": "2026-06-30T05:01:32.918554"
}