{
  "ticker": "GLW",
  "company": "Corning Incorporated",
  "analysis_date": "2026-04-08",
  "source_file": "cache/2026-04-08/candidates/news/GLW.json",
  "summary": {
    "total_articles": 9,
    "bullish_count": 7,
    "bearish_count": 1,
    "neutral_count": 1,
    "overall_sentiment": "bullish",
    "key_theme": "受惠於 AI 資料中心對光纖基礎設施的強勁需求，以及與 Meta 的重大合作案，推動市場對 Corning 的估值重估。"
  },
  "bullish": [
    {
      "rank": 1,
      "title": "Corning (GLW) Is Up 9.3% After $6 Billion Meta AI Fiber Deal - Has The Bull Case Changed?",
      "publisher": "Yahoo",
      "date": "2026-04-03 13:07",
      "impact": "high",
      "category": "市場擴張",
      "reason": "Corning 與 Meta 達成 60 億美元的光纖合約，直接證明了 AI 基礎設施需求對公司營收的實質貢獻，是近期股價上漲的核心驅動力。"
    },
    {
      "rank": 2,
      "title": "How The Corning (GLW) Narrative Is Shifting With AI Fiber Deals And Richer Valuation Assumptions",
      "publisher": "Yahoo",
      "date": "2026-04-03 16:17",
      "impact": "high",
      "category": "財務分析",
      "reason": "分析師將 Corning 的公平價值模型從 114.46 美元上調至 129.64 美元，反映市場對其 AI 相關業務成長潛力的重新定價。"
    },
    {
      "rank": 3,
      "title": "Will Corning (GLW) Beat Estimates Again in Its Next Earnings Report?",
      "publisher": "Yahoo",
      "date": "2026-04-06 16:10",
      "impact": "medium",
      "category": "財報公布",
      "reason": "Corning 擁有良好的財報驚喜歷史，市場預期其在 AI 需求帶動下，下一季財報仍有機會優於預期。"
    },
    {
      "rank": 4,
      "title": "Can Corning's Enhanced Healthcare Portfolio Boost Its Shares?",
      "publisher": "Yahoo",
      "date": "2026-04-07 15:14",
      "impact": "medium",
      "category": "產品發布",
      "reason": "公司在醫療保健領域的先進玻璃與生物製程解決方案，為其核心光學業務之外提供了多元化的成長引擎。"
    },
    {
      "rank": 5,
      "title": "Corning’s (GLW) a Company Of The Future, Says Jim Cramer",
      "publisher": "Yahoo",
      "date": "2026-04-07 06:52",
      "impact": "low",
      "category": "市場動態",
      "reason": "知名財經評論員 Jim Cramer 的背書提升了市場對該公司作為未來科技基礎設施供應商的信心。"
    },
    {
      "rank": 6,
      "title": "Buy and Hold Forever This Unknown AI Stock up 200%",
      "publisher": "Yahoo",
      "date": "2026-04-06 15:02",
      "impact": "low",
      "category": "市場動態",
      "reason": "強調 Corning 作為現代數位世界不可或缺的物理基礎設施供應商，具備長期投資價值。"
    },
    {
      "rank": 7,
      "title": "Why Is Corning (GLW) Stock Soaring Today",
      "publisher": "Yahoo",
      "date": "2026-04-02 00:47",
      "impact": "medium",
      "category": "市場動態",
      "reason": "反映市場對公司近期業務轉型與 AI 相關訂單的積極反應，單日股價上漲 5.4 %。"
    }
  ],
  "bearish": [
    {
      "rank": 1,
      "title": "Corning Stock Rises 60.6% in 3 Months: How to Play the Stock",
      "publisher": "Yahoo",
      "date": "2026-04-02 12:53",
      "impact": "medium",
      "category": "市場動態",
      "reason": "儘管股價表現強勁，但報告提醒投資人需注意客戶過度集中、宏觀經濟風險以及汽車業務疲軟等潛在負面因素。"
    }
  ],
  "neutral": [
    {
      "rank": 1,
      "title": "Truist Cautious on Corning (GLW) Despite Strong AI and Cloud Spending Tailwinds",
      "publisher": "Yahoo",
      "date": "2026-04-02 01:28",
      "impact": "low",
      "category": "財務分析",
      "reason": "Truist 對該股持謹慎態度，顯示儘管 AI 趨勢強勁，但市場對其估值與未來成長持續性仍存在分歧。"
    }
  ],
  "_schema_version": "1.1"
}