{
  "ticker": "AMD",
  "company": "AMD",
  "analysis_date": "2026-04-01",
  "source_file": "cache/2026-04-01/competitors/news/AMD.json",
  "summary": {
    "total_articles": 20,
    "bullish_count": 9,
    "bearish_count": 6,
    "neutral_count": 5,
    "overall_sentiment": "bullish",
    "key_theme": "儘管面臨短期市場波動與地緣政治風險，AMD 在 AI 晶片需求強勁、與 Samsung 的 HBM4 合作以及分析師給予的高目標價支撐下，長期成長前景依然看好。"
  },
  "bullish": [
    {
      "rank": 1,
      "title": "AMD Stock Gains Momentum As UBS Eyes 54% Upside On AI Megadeals",
      "publisher": "Benzinga",
      "date": "2026-03-30 08:27",
      "impact": "high",
      "category": "分析師評級",
      "reason": "瑞銀 (UBS) 給予 AMD 目標價 310 美元，預期有 54% 的上漲空間，主要基於 GW 級 AI 資料中心訂單的強勁成長動能。"
    },
    {
      "rank": 2,
      "title": "AMD And Samsung Partnership Adds New Piece To AI Supply Story",
      "publisher": "Yahoo",
      "date": "2026-03-30 05:05",
      "impact": "high",
      "category": "策略合作",
      "reason": "AMD 與三星簽署合作備忘錄，將供應下一代 HBM4 記憶體，此舉有助於解決 AI 晶片關鍵供應鏈瓶頸，提升競爭力。"
    },
    {
      "rank": 3,
      "title": "Why the Second Half of 2026 Could Be Huge for AMD Stock",
      "publisher": "Yahoo",
      "date": "2026-03-30 20:20",
      "impact": "medium",
      "category": "產品發布",
      "reason": "預期 2026 年下半年隨著下一代晶片產品線的推出，將顯著推動營收成長。"
    },
    {
      "rank": 4,
      "title": "AI Startup “Upstage” in Talks to Purchase 10,000 Advanced Micro Devices (AMD) Chips in Korea",
      "publisher": "Yahoo",
      "date": "2026-03-31 17:39",
      "impact": "medium",
      "category": "市場擴張",
      "reason": "AI 新創公司 Upstage 洽談採購 1 萬顆 AMD 晶片，顯示其在韓國市場的 AI 晶片需求持續擴大。"
    },
    {
      "rank": 5,
      "title": "As Meta Doubles Down on Data Center Investment, AMD and American Tower Could Be the Top Stocks to Buy",
      "publisher": "Yahoo",
      "date": "2026-03-29 14:00",
      "impact": "medium",
      "category": "市場動態",
      "reason": "Meta 持續擴大資料中心投資，預期將帶動 AMD 高階 Instinct GPU 的需求成長。"
    },
    {
      "rank": 6,
      "title": "AMD Gets Fresh Boost on AI Growth Outlook",
      "publisher": "Yahoo",
      "date": "2026-03-30 15:13",
      "impact": "low",
      "category": "市場動態",
      "reason": "分析師普遍看好資料中心與 AI 需求加速，為股價提供支撐。"
    },
    {
      "rank": 7,
      "title": "Why Advanced Micro Devices (AMD) is a Top Stock for the Long-Term",
      "publisher": "Yahoo",
      "date": "2026-03-30 13:30",
      "impact": "low",
      "category": "投資建議",
      "reason": "基於正面的獲利展望，AMD 被列入長期投資組合的焦點名單。"
    },
    {
      "rank": 8,
      "title": "2 AI Chip Stocks I'd Buy Before Their Next Earnings Reports",
      "publisher": "Yahoo",
      "date": "2026-03-31 12:02",
      "impact": "low",
      "category": "投資建議",
      "reason": "將 AMD 與 Broadcom 並列為財報公布前值得關注的頂級半導體股。"
    }
  ],
  "bearish": [
    {
      "rank": 1,
      "title": "Cathie Wood Going Cold On Big Tech? Ark Sells Nvidia, AMD, Meta And Google Stock",
      "publisher": "Yahoo",
      "date": "2026-03-29 13:31",
      "impact": "medium",
      "category": "機構持倉",
      "reason": "Cathie Wood 領導的 Ark Invest 減持 AMD 等科技巨頭股票，可能引發市場對高估值科技股的獲利了結擔憂。"
    },
    {
      "rank": 2,
      "title": "AMD's Gaming Revenues Set to Decelerate: What's the Path Ahead?",
      "publisher": "Yahoo",
      "date": "2026-03-31 15:10",
      "impact": "medium",
      "category": "財報分析",
      "reason": "儘管 GPU 需求強勁，但遊戲部門營收出現季減，且半客製化業務疲軟，對短期營收成長構成壓力。"
    },
    {
      "rank": 3,
      "title": "AMD stock sends valuation signal for first time in 3 years",
      "publisher": "Yahoo",
      "date": "2026-03-30 17:47",
      "impact": "medium",
      "category": "市場動態",
      "reason": "技術指標顯示 AMD 估值出現三年來首次的警示訊號，可能暗示股價過熱。"
    },
    {
      "rank": 4,
      "title": "Nvidia, AMD and Intel Lead Chip Stocks Sell-Off Amid Middle East Tension",
      "publisher": "Yahoo",
      "date": "2026-03-27 19:44",
      "impact": "medium",
      "category": "市場動態",
      "reason": "地緣政治緊張局勢導致半導體類股遭到拋售，AMD 作為高 beta 係數股票受影響較大。"
    },
    {
      "rank": 5,
      "title": "Why Advanced Micro Devices (AMD) Dipped More Than Broader Market Today",
      "publisher": "Yahoo",
      "date": "2026-03-30 21:45",
      "impact": "low",
      "category": "市場動態",
      "reason": "AMD 當日股價下跌 2.95%，表現弱於大盤，反映短期賣壓。"
    },
    {
      "rank": 6,
      "title": "Analyst Signals Caution Amid Demand Concerns For Advanced Micro Devices (AMD)",
      "publisher": "Yahoo",
      "date": "2026-03-28 15:18",
      "impact": "low",
      "category": "分析師評級",
      "reason": "有分析師對 AMD 的需求前景表示謹慎，提醒投資人關注潛在的成長放緩風險。"
    }
  ],
  "neutral": [
    {
      "rank": 1,
      "title": "Lisa Su Hosts Howard Lutnick As Commerce Department Highlights 'Gold Standard' American Tech Stack",
      "publisher": "Yahoo",
      "date": "2026-03-29 11:31",
      "impact": "low",
      "category": "高層動態",
      "reason": "AMD 執行長蘇姿丰與商務部長 Howard Lutnick 會面，討論美國科技產業發展，屬於例行性政策溝通。"
    },
    {
      "rank": 2,
      "title": "Intel Price Hikes And Supply Strains Test Recent Share Momentum",
      "publisher": "Yahoo",
      "date": "2026-03-28 15:05",
      "impact": "low",
      "category": "市場動態",
      "reason": "Intel 與 AMD 同步調漲 CPU 價格，反映供應鏈壓力，對兩者影響中性。"
    },
    {
      "rank": 3,
      "title": "AMD vs Intel: Which Stock Will Lead in 2026?",
      "publisher": "Yahoo",
      "date": "2026-03-30 13:40",
      "impact": "low",
      "category": "產業分析",
      "reason": "對比 AMD 與 Intel 的競爭優勢，屬於產業競爭分析，無直接股價影響。"
    },
    {
      "rank": 4,
      "title": "Xanadu IPO: CEO on AMD partnership, quantum computing, and more",
      "publisher": "Yahoo",
      "date": "2026-03-27 21:18",
      "impact": "low",
      "category": "策略合作",
      "reason": "提及與量子運算公司 Xanadu 的合作，但目前對 AMD 營收貢獻尚不明顯。"
    },
    {
      "rank": 5,
      "title": "Intel Slides 5%, AMD Drops 3%: The Semiconductor Sector Is at a Crossroads",
      "publisher": "Yahoo",
      "date": "2026-03-30 17:39",
      "impact": "low",
      "category": "市場動態",
      "reason": "報導半導體板塊整體回調，AMD 隨產業趨勢波動。"
    }
  ],
  "_schema_version": "1.1"
}