{
  "current_price": 50.38,
  "ma50": 46.16,
  "ma200": 35.29,
  "high_52w": 54.32,
  "low_52w": 18.13,
  "avg_vol_20d": 90502985,
  "current_vol": 117134200,
  "change_3mo_pct": 18.18,
  "ma20": 45.29,
  "rsi14": 59.36,
  "macd": 0.204,
  "macd_signal": -0.243,
  "bb_upper": 49.46,
  "bb_lower": 41.13,
  "bb_pct": 1.11,
  "atr14": 2.9,
  "vol_ratio": 1.29,
  "trend_status": "RECOVERY",
  "tech_score": 71.0,
  "var_95": -5.71,
  "sortino": 2.47,
  "max_drawdown": 24.2,
  "beta": 1.35,
  "calmar": 4.29,
  "risk_score": 73.0,
  "_cached_at": "2026-04-06T12:55:12.151337"
}