{
  "current_price": 95.22,
  "ma50": 105.35,
  "ma200": 120.66,
  "high_52w": 140.8,
  "low_52w": 89.24,
  "avg_vol_20d": 1659755,
  "current_vol": 1886400,
  "change_3mo_pct": -15.81,
  "ma20": 98.94,
  "rsi14": 26.36,
  "macd": -4.41,
  "macd_signal": -4.121,
  "bb_upper": 113.05,
  "bb_lower": 84.83,
  "bb_pct": 0.37,
  "atr14": 3.56,
  "vol_ratio": 1.14,
  "trend_status": "DOWNTREND",
  "tech_score": 25.0,
  "var_95": -3.51,
  "sortino": -1.01,
  "max_drawdown": 36.6,
  "beta": 0.59,
  "calmar": -0.39,
  "risk_score": 43.0,
  "_cached_at": "2026-04-06T12:55:33.458980"
}