{
  "marketCap": 4231443775488,
  "enterpriseValue": 4171441635328,
  "trailingPE": 32.357075,
  "forwardPE": 25.855812,
  "priceToSalesTrailing12Months": 10.504135,
  "pegRatio": 2.36,
  "priceToBook": 10.181934,
  "beta": 1.128,
  "dividendYield": 0.24,
  "trailingEps": 10.81,
  "forwardEps": 13.5281,
  "revenueGrowth": 0.18,
  "earningsGrowth": 0.311,
  "grossMargins": 0.59652,
  "operatingMargins": 0.31568,
  "profitMargins": 0.32810003,
  "totalRevenue": 402835996672,
  "freeCashflow": 38088376320,
  "operatingCashflow": 164713005056,
  "totalDebt": 66995998720,
  "totalCash": 126843002880,
  "debtToEquity": 16.133,
  "currentRatio": 2.005,
  "returnOnEquity": 0.35705003,
  "returnOnAssets": 0.15427,
  "longName": "Alphabet Inc.",
  "shortName": "Alphabet Inc.",
  "sector": "Communication Services",
  "industry": "Internet Content & Information",
  "longBusinessSummary": "Alphabet Inc. 的業務版圖涵蓋美國、歐洲、中東、非洲、亞太地區、加拿大及拉丁美洲，主要透過 Google Services、Google Cloud 及 Other Bets 三大部門營運。\n\nGoogle Services 部門提供多元產品與服務，包括廣告、Android、Chrome、硬體裝置、Gmail、Google Drive、Google Maps、Google Photos、Google Play、搜尋引擎及 YouTube。該部門業務亦涵蓋 Google Play 與 YouTube 的應用程式銷售、應用程式內購及數位內容；並銷售硬體裝置，以及提供 YouTube 消費性訂閱服務（如 YouTube TV、YouTube Music 與 Premium、NFL Sunday Ticket 及 Google One）。\n\nGoogle Cloud 部門提供 AI 解決方案的用量計費與訂閱服務，包含 AI 基礎設施、Vertex AI 平台及 Gemini 企業版。此外，該部門亦提供網路安全、數據分析服務，以及包含 Calendar、Gmail、Docs、Drive 與 Meet 等企業雲端通訊與協作工具的 Google Workspace，並提供其他企業級服務。\n\nOther Bets 部門則致力於交通運輸與網際網路服務。Alphabet Inc. 成立於 1998 年，總部位於加州山景城。",
  "recommendationMean": 1.39394,
  "company_name": "Alphabet Inc.",
  "fcf_margin": 9.46,
  "net_debt": -59847004160,
  "next_earnings_date": "2026-04-29",
  "fund_score": 67.0,
  "fund_score_details": {
    "rev_growth_yoy": 18.0,
    "gross_margin": 59.65200000000001,
    "fcf_margin": 9.455057798872078,
    "roic_proxy": 35.7,
    "forward_peg": 2.36,
    "debt_equity": 0.16,
    "analyst_rec": 1.39394,
    "health_score": 67.0,
    "source": "yfinance"
  },
  "_cached_at": "2026-04-29T04:28:35.246310"
}