{
  "current_price": 770.76,
  "ma50": 523.54,
  "ma200": 388.74,
  "high_52w": 889.03,
  "low_52w": 182.09,
  "avg_vol_20d": 677100,
  "current_vol": 732400,
  "change_3mo_pct": 77.33,
  "ma20": 670.46,
  "rsi14": 70.49,
  "macd": 105.151,
  "macd_signal": 95.502,
  "bb_upper": 1029.76,
  "bb_lower": 311.16,
  "bb_pct": 0.64,
  "atr14": 67.58,
  "vol_ratio": 1.08,
  "trend_status": "UPTREND",
  "tech_score": 80.0,
  "var_95": -6.37,
  "sortino": 3.85,
  "max_drawdown": 31.0,
  "beta": 1.64,
  "calmar": 5.55,
  "risk_score": 60.0,
  "_cached_at": "2026-05-19T05:02:06.665852"
}