{
  "ticker": "VOO",
  "company": "S&P 500",
  "analysis_date": "2026-06-11",
  "source_file": "cache/2026-06-11/holdings/news/VOO.json",
  "summary": {
    "total_articles": 20,
    "bullish_count": 5,
    "bearish_count": 7,
    "neutral_count": 8,
    "overall_sentiment": "mixed",
    "key_theme": "VOO 規模突破 1 兆美元里程碑，但市場對於指數集中度風險、高估值以及被動投資策略的長期有效性存在顯著分歧。"
  },
  "bullish": [
    {
      "rank": 1,
      "title": "Why Vanguard’s VOO Won the Trillion-Dollars-in-Assets Race",
      "publisher": "Yahoo",
      "date": "2026-06-05 22:55",
      "impact": "high",
      "category": "市場動態",
      "reason": "VOO 資產管理規模突破 1 兆美元，顯示其作為低成本指數投資工具的市場主導地位與投資人高度信任。"
    },
    {
      "rank": 2,
      "title": "This Vanguard ETF Just Made Stock Market History. Here's Why It's Still a Fantastic Investment in 2026.",
      "publisher": "Yahoo",
      "date": "2026-06-07 12:50",
      "impact": "medium",
      "category": "市場動態",
      "reason": "強調 VOO 在 2026 年仍是長期投資者的核心配置，其追蹤 S&P 500 的穩定性與低費用率優勢持續吸引資金流入。"
    },
    {
      "rank": 3,
      "title": "Marvell's S&P 500 Inclusion Could Spark Fresh ETF Buying Despite Valuation Concerns",
      "publisher": "Benzinga",
      "date": "2026-06-08 11:46",
      "impact": "medium",
      "category": "成分股調整",
      "reason": "Marvell (MRVL) 被納入 S&P 500 指數，將迫使追蹤該指數的 VOO 等 ETF 進行被動買入，短期內對成分股具備支撐效果。"
    },
    {
      "rank": 4,
      "title": "5 'Insane' Growth Stocks Already Tripled Or More This Year",
      "publisher": "Yahoo",
      "date": "2026-06-09 11:26",
      "impact": "low",
      "category": "市場動態",
      "reason": "S&P 500 內部分成長股表現強勁，帶動整體指數績效，反映市場對 AI 驅動的獲利成長預期。"
    },
    {
      "rank": 5,
      "title": "Guide to the S&P 500 ETF Investing",
      "publisher": "Yahoo",
      "date": "2026-06-09 16:00",
      "impact": "low",
      "category": "市場動態",
      "reason": "指出 S&P 500 在 2026 年受惠於 AI 相關獲利強勁，展現出極高的市場韌性。"
    }
  ],
  "bearish": [
    {
      "rank": 1,
      "title": "The VOO ETF Just Hit $1 Trillion in AUM. That’s a Terrifying Warning on ‘Terminal’ Index Concentration",
      "publisher": "Yahoo",
      "date": "2026-06-05 13:00",
      "impact": "high",
      "category": "市場風險",
      "reason": "資產規模過大引發市場對指數集中度風險的擔憂，分析師警告若市場反轉，被動資金流出可能導致流動性問題。"
    },
    {
      "rank": 2,
      "title": "The S&P 500 Is Lying To You, The Market Crashed A While Ago, And I Have The Receipts",
      "publisher": "SeekingAlpha",
      "date": "2026-06-09 08:30",
      "impact": "medium",
      "category": "市場分析",
      "reason": "質疑 S&P 500 指數表現失真，指出多數成分股表現落後於國庫券，暗示市場廣度不足，存在隱性崩盤風險。"
    },
    {
      "rank": 3,
      "title": "Headwinds Building But This Stat Says Stocks Go Higher",
      "publisher": "SeekingAlpha",
      "date": "2026-06-09 08:57",
      "impact": "medium",
      "category": "市場分析",
      "reason": "指出目前 S&P 500 估值處於歷史高位，且出現熊市訊號，儘管短期仍有動能，但長期回調風險正在累積。"
    },
    {
      "rank": 4,
      "title": "Forget VOO: Fidelity’s Tech ETF Is Up 29% While the Broad Market Lags",
      "publisher": "Yahoo",
      "date": "2026-06-10 11:15",
      "impact": "low",
      "category": "競爭分析",
      "reason": "透過比較 Fidelity 的科技類 ETF (FTEC) 的高報酬，凸顯 VOO 作為大盤指數型產品在特定牛市環境下績效不如產業型 ETF。"
    },
    {
      "rank": 5,
      "title": "1 Costly Mistake Too Many Investors Make With the Vanguard S&P 500 ETF (VOO)",
      "publisher": "Yahoo",
      "date": "2026-06-07 19:05",
      "impact": "low",
      "category": "投資策略",
      "reason": "提醒投資人對 VOO 的配置可能存在誤解，過度依賴單一指數可能導致資產配置缺乏多樣性。"
    },
    {
      "rank": 6,
      "title": "Is the Vanguard S&P 500 ETF Still Worth Buying Right Now?",
      "publisher": "Yahoo",
      "date": "2026-06-05 20:05",
      "impact": "low",
      "category": "投資策略",
      "reason": "針對高估值環境提出質疑，建議投資人評估是否應等待更好的進場點，而非盲目追高。"
    },
    {
      "rank": 7,
      "title": "Should You Buy the Vanguard S&P 500 ETF As the Market Hits New Highs?",
      "publisher": "Yahoo",
      "date": "2026-06-05 13:20",
      "impact": "low",
      "category": "投資策略",
      "reason": "與前述新聞觀點一致，針對歷史高點的市場環境，對現階段進場 VOO 的風險報酬比提出審慎看法。"
    }
  ],
  "neutral": [
    {
      "rank": 1,
      "title": "VOO vs. VTI: Should You Own the S&P 500 or the Entire Market?",
      "publisher": "Yahoo",
      "date": "2026-06-10 18:52",
      "impact": "low",
      "category": "投資策略",
      "reason": "探討 VOO 與 VTI 的選擇差異，屬於常見的投資組合配置教學，對股價無直接影響。"
    },
    {
      "rank": 2,
      "title": "Vanguard and iShares S&P 500 ETFs Compared: Is There Really a Difference?",
      "publisher": "Yahoo",
      "date": "2026-06-10 15:55",
      "impact": "low",
      "category": "競爭分析",
      "reason": "比較 Vanguard 與 iShares 的 S&P 500 ETF 差異，屬於產品規格分析，對 VOO 本身無利多或利空影響。"
    },
    {
      "rank": 3,
      "title": "The Vanguard S&P 500 ETF Is Unstoppable -- But There's 1 ETF I Like Even More",
      "publisher": "Yahoo",
      "date": "2026-06-09 16:05",
      "impact": "low",
      "category": "投資策略",
      "reason": "作者表達個人偏好，認為全市場 ETF 優於 S&P 500，屬於觀點分享，對 VOO 股價影響有限。"
    },
    {
      "rank": 4,
      "title": "VOO vs SPY vs IVV: Which S 500 ETF Should You Buy in 2026?",
      "publisher": "Yahoo",
      "date": "2026-06-08 21:58",
      "impact": "low",
      "category": "競爭分析",
      "reason": "針對追蹤相同指數的 ETF 進行比較，屬於投資人教育性質的內容。"
    },
    {
      "rank": 5,
      "title": "These 3 S&P 500 ETFs Are Nearly Identical But After Doing the Math One of Them Saves You Money Over a Lifetime",
      "publisher": "Yahoo",
      "date": "2026-06-09 01:51",
      "impact": "low",
      "category": "投資策略",
      "reason": "分析不同 ETF 的費用率差異，對 VOO 的長期持有成本進行客觀比較。"
    },
    {
      "rank": 6,
      "title": "VOO vs. SPY: Which ETF Is the Best Way to Buy the S&P 500?",
      "publisher": "Yahoo",
      "date": "2026-06-08 04:20",
      "impact": "low",
      "category": "競爭分析",
      "reason": "探討不同 S&P 500 ETF 的流動性與結構差異，屬於中性市場分析。"
    }
  ],
  "_schema_version": "1.1"
}