{
  "current_price": 83.36,
  "ma50": 80.04,
  "ma200": 70.64,
  "high_52w": 88.77,
  "low_52w": 52.95,
  "avg_vol_20d": 313120,
  "current_vol": 741500,
  "change_3mo_pct": 13.26,
  "ma20": 81.78,
  "rsi14": 58.52,
  "macd": 1.293,
  "macd_signal": 1.168,
  "bb_upper": 84.25,
  "bb_lower": 79.31,
  "bb_pct": 0.82,
  "atr14": 2.7,
  "vol_ratio": 2.37,
  "trend_status": "UPTREND",
  "tech_score": 93.0,
  "var_95": -3.25,
  "sortino": 2.0,
  "max_drawdown": 22.5,
  "beta": 1.13,
  "calmar": 2.3,
  "risk_score": 86.0,
  "_cached_at": "2026-06-25T05:08:31.702062"
}