{
  "ticker": "HUBS",
  "company": "HubSpot, Inc.",
  "analysis_date": "2026-03-26",
  "source_file": "cache/2026-03-26/competitors/news/HUBS.json",
  "summary": {
    "total_articles": 6,
    "bullish_count": 1,
    "bearish_count": 3,
    "neutral_count": 2,
    "overall_sentiment": "bearish",
    "key_theme": "市場對 HubSpot 過去一年股價大幅回調後的估值與成長潛力存在分歧，短期內面臨投資人信心不足與股價下行壓力。"
  },
  "bullish": [
    {
      "rank": 1,
      "title": "HubSpot Focusing More on AI: A Smarter CRM Growth Story Brewing?",
      "publisher": "Zacks",
      "date": "2026-03-23",
      "impact": "medium",
      "category": "產品發展",
      "reason": "HubSpot 積極投入 AI 領域，市場預期這將提升 CRM 平台的智慧化程度，進而成為推動未來營收成長的關鍵驅動力。"
    }
  ],
  "bearish": [
    {
      "rank": 1,
      "title": "Domo, Upland Software, Pegasystems, HubSpot, and PagerDuty Shares Are Falling, What You Need To Know",
      "publisher": "StockStory",
      "date": "2026-03-24",
      "impact": "high",
      "category": "市場動態",
      "reason": "該報導涵蓋了多個軟體股的集體下跌，反映出市場對 SaaS 產業整體估值修正的擔憂，HubSpot 作為其中一員受到板塊輪動的負面影響。"
    },
    {
      "rank": 2,
      "title": "HubSpot (HUBS) Fell on Investors’ Concerns",
      "publisher": "Insider Monkey",
      "date": "2026-03-23",
      "impact": "medium",
      "category": "市場動態",
      "reason": "明確指出投資人對公司營運或前景的擔憂導致股價下跌，反映出市場信心脆弱，是近期股價疲軟的主因。"
    },
    {
      "rank": 3,
      "title": "Is It Time To Revisit HubSpot (HUBS) After A 56% One Year Share Price Slide",
      "publisher": "Simply Wall St.",
      "date": "2026-03-20",
      "impact": "medium",
      "category": "股價表現",
      "reason": "過去一年股價下跌 56 % 的數據顯示出強烈的長期空頭趨勢，儘管提及重新評估的機會，但巨大的跌幅本身即代表市場對其成長動能的質疑。"
    }
  ],
  "neutral": [
    {
      "rank": 1,
      "title": "Evaluating HubSpot (HUBS) After A Mixed Share Price Run And Undervaluation Debate",
      "publisher": "Simply Wall St.",
      "date": "2026-03-20",
      "impact": "low",
      "category": "財務分析",
      "reason": "文章探討了股價被低估的可能性與混合的市場表現，提供了多空雙方的觀點，未給出明確的買賣建議，屬於中立的分析報告。"
    },
    {
      "rank": 2,
      "title": "Do You Believe in the Upside Potential of HubSpot (HUBS)?",
      "publisher": "Insider Monkey",
      "date": "2026-03-20",
      "impact": "low",
      "category": "市場觀點",
      "reason": "以提問方式引導讀者思考 HubSpot 的上漲潛力，並未提供具體的利多或利空證據，僅作為市場情緒的觀察指標。"
    }
  ],
  "_schema_version": "1.1"
}