{
  "current_price": 0.29,
  "ma50": 0.35,
  "ma200": 0.88,
  "high_52w": 3.0,
  "low_52w": 0.22,
  "avg_vol_20d": 15550155,
  "current_vol": 26255400,
  "change_3mo_pct": 1.38,
  "ma20": 0.33,
  "rsi14": 46.71,
  "macd": -0.014,
  "macd_signal": -0.012,
  "bb_upper": 0.38,
  "bb_lower": 0.27,
  "bb_pct": 0.21,
  "atr14": 0.05,
  "vol_ratio": 1.69,
  "trend_status": "DOWNTREND",
  "tech_score": 20.0,
  "var_95": -9.83,
  "sortino": -1.18,
  "max_drawdown": 92.8,
  "beta": 5.52,
  "calmar": -0.73,
  "risk_score": 0.0,
  "_cached_at": "2026-06-18T05:55:05.535976"
}