{
  "articles": [
    {
      "title": "Quanta (PWR) Shares Up After It Was Called A “Hidden Giant” — Quanta Services Inc. (NYSE:PWR) is one of the 14 Stocks That Will Skyrocket. This is another stock that’s part of the ad",
      "link": "https://finnhub.io/api/news?id=8fd1160bff600adfcd7a852ef105291766e5bfecb9d8b8117854c3d90c25ce2d",
      "publisher": "Yahoo",
      "date": "2026-05-11 15:27",
      "_source": "finnhub",
      "_score": 14.4,
      "symbol": "PWR"
    },
    {
      "title": "Cantor Fitzgerald Maintains Overweight on Quanta Services, Raises Price Target to $901 — Cantor Fitzgerald  analyst Manish A. Somaiya   maintains Quanta Services (NYSE:PWR) with a Overweight and raises the pri",
      "link": "https://finnhub.io/api/news?id=f6d1b52d7d3212ddd8b43f739d9c1045b110c378bf1ea5c41b2fad0043475b67",
      "publisher": "Benzinga",
      "date": "2026-05-11 09:29",
      "_source": "finnhub",
      "_score": 12.96,
      "symbol": "PWR"
    },
    {
      "title": "Is It Too Late To Consider Quanta Services (PWR) After Its Strong Share Price Run? — Investors may be wondering whether Quanta Services at US$750.73 is still offering value, or if the easy money has alread",
      "link": "https://finnhub.io/api/news?id=165952d9352217077534af9d89403f504bc7f630e5523a1279edb841aa998f87",
      "publisher": "Yahoo",
      "date": "2026-05-10 15:13",
      "_source": "finnhub",
      "_score": 12.8,
      "symbol": "PWR"
    },
    {
      "title": "Quanta (PWR): The Best Construction Stock for Data Center Infrastructure — Quanta Services, Inc. (NYSE:PWR) is one of the 10 Best Construction Stocks for Data Center Infrastructure. On May 4, 202",
      "link": "https://finnhub.io/api/news?id=2f42d36d84704f27e915d088ca018ee9ce8e64b356b9a479283fa08c1d99d13a",
      "publisher": "Yahoo",
      "date": "2026-05-09 10:54",
      "_source": "finnhub",
      "_score": 11.2,
      "symbol": "PWR"
    },
    {
      "title": "Looking for a Growth Stock? 3 Reasons Why Quanta Services (PWR) is a Solid Choice — Quanta Services (PWR) possesses solid growth attributes, which could help it handily outperform the market.",
      "link": "https://finnhub.io/api/news?id=b41286a845468d628b2b0ab30c656af704f38c2ab92fff95116b4387ae1f5238",
      "publisher": "Yahoo",
      "date": "2026-05-08 16:45",
      "_source": "finnhub",
      "_score": 9.6,
      "symbol": "PWR"
    },
    {
      "title": "Are You Looking for a Top Momentum Pick? Why Quanta Services (PWR) is a Great Choice — Does Quanta Services (PWR) have what it takes to be a top stock pick for momentum investors? Let's find out.",
      "link": "https://finnhub.io/api/news?id=cae1d134a4cc658160a1a996902e18a3c3ff7716a9aa2c15d139b707a5d90016",
      "publisher": "Yahoo",
      "date": "2026-05-08 16:00",
      "_source": "finnhub",
      "_score": 9.6,
      "symbol": "PWR"
    },
    {
      "title": "Is Quanta Services (PWR) Stock Outpacing Its Construction Peers This Year? — Here is how Quanta Services (PWR) and Tutor Perini (TPC) have performed compared to their sector so far this year.",
      "link": "https://finnhub.io/api/news?id=eda22ef46603d642879aaa645658c9f77e73370c4c3673eb1e04bf76f0ba574b",
      "publisher": "Yahoo",
      "date": "2026-05-08 13:40",
      "_source": "finnhub",
      "_score": 9.6,
      "symbol": "PWR"
    },
    {
      "title": "Brokers Suggest Investing in Quanta Services (PWR): Read This Before Placing a Bet — Based on the average brokerage recommendation (ABR), Quanta Services (PWR) should be added to one's portfolio. Wall Stre",
      "link": "https://finnhub.io/api/news?id=5dc36c960fa454e9a8cf0b4f2c71aa88a488de3b9cc3d177fcf5f7e96eec6eeb",
      "publisher": "Yahoo",
      "date": "2026-05-08 13:30",
      "_source": "finnhub",
      "_score": 9.6,
      "symbol": "PWR"
    },
    {
      "title": "Quanta Stock Climbs 36% in a Month: Should You Buy Now or Wait? — Can PWR stock sustain its rally as AI-driven power demand and record backlog fuel long-term growth?",
      "link": "https://finnhub.io/api/news?id=3f3d9ab3c196715858e81534a2b3592576f4427fc8e0e3a6b68d563941ddf5d3",
      "publisher": "Yahoo",
      "date": "2026-05-07 16:00",
      "_source": "finnhub",
      "_score": 8.0,
      "symbol": "PWR"
    },
    {
      "title": "Quanta Services (PWR) Reports Record Q1 2026 Revenue of $7.87B — Quanta Services Inc. (NYSE:PWR) is one of the best growth stocks to invest in for the next 2 years. On April 30, Quanta ",
      "link": "https://finnhub.io/api/news?id=566cc3c617989d1ca39e2bb47b7927931451866dec22bcb779d3e3ed5aa91656",
      "publisher": "Yahoo",
      "date": "2026-05-07 04:56",
      "_source": "finnhub",
      "_score": 8.0,
      "symbol": "PWR"
    },
    {
      "title": "Quanta Services (PWR) Is Up 22.3% After Raising 2026 Outlook On Record Infrastructure Backlog - What's Changed — In late April 2026, Quanta Services reported first-quarter 2026 results showing sales of US$7,874.79 million and net inc",
      "link": "https://finnhub.io/api/news?id=ea92c4c6cb16635568bd8e1c46d9f18ee24c3858d6993adfeafb416fb095ab00",
      "publisher": "Yahoo",
      "date": "2026-05-06 18:20",
      "_source": "finnhub",
      "_score": 6.399999999999999,
      "symbol": "PWR"
    },
    {
      "title": "The Smartest Energy Stocks to Buy With $1,000 Right Now — Vistra and Quanta Services will benefit from soaring energy demand.",
      "link": "https://finnhub.io/api/news?id=b3f893de25e2e98e429e6602246630397786fed32d97eda156d5d6aa48c9b9cd",
      "publisher": "Yahoo",
      "date": "2026-05-06 20:50",
      "_source": "finnhub",
      "_score": 5.759999999999999,
      "symbol": "PWR"
    }
  ],
  "_cached_at": "2026-05-13T04:45:52.812260"
}