{
  "ticker": "AEP",
  "company": "American Electric Power",
  "analysis_date": "2026-03-12",
  "source_file": "cache/2026-03-12/competitors/news/AEP.json",
  "summary": {
    "total_articles": 12,
    "bullish_count": 6,
    "bearish_count": 1,
    "neutral_count": 5,
    "overall_sentiment": "bullish",
    "key_theme": "公司透過擴大 720 億美元的電網與再生能源資本支出，積極布局 AI 資料中心需求，並獲得分析師調升目標價的正面評價。"
  },
  "bullish": [
    {
      "rank": 1,
      "title": "Evercore ISI Group Maintains Outperform on American Electric Power, Raises Price Target to $153",
      "publisher": "Benzinga",
      "date": "2026-03-05 09:54",
      "impact": "high",
      "category": "分析師評級",
      "reason": "Evercore ISI 分析師 Nicholas Amicucci 維持「優於大盤」評級並調升目標價至 153 美元，顯示市場對其長期成長潛力具備高度信心。"
    },
    {
      "rank": 2,
      "title": "American Electric Drives Growth Through Investments and Renewables",
      "publisher": "Yahoo",
      "date": "2026-03-06 15:56",
      "impact": "high",
      "category": "資本支出",
      "reason": "公司計畫至 2030 年投入 720 億美元於電網與再生能源，此舉將直接推動費率基礎（rate-base）成長，為長期獲利提供明確動能。"
    },
    {
      "rank": 3,
      "title": "American Electric Power Targets AI Data Center Growth With Expanded Capex",
      "publisher": "Simply Wall St.",
      "date": "2026-03-02 09:10",
      "impact": "medium",
      "category": "市場擴張",
      "reason": "針對 AI 資料中心電力需求的擴張策略，展現公司在電力基礎設施領域的戰略前瞻性，有助於提升未來營收結構。"
    },
    {
      "rank": 4,
      "title": "American Electric Stock: Is AEP Outperforming the Utilities Sector?",
      "publisher": "Yahoo",
      "date": "2026-03-05 12:57",
      "impact": "medium",
      "category": "市場動態",
      "reason": "AEP 近期表現優於公用事業板塊，反映出投資人對其營運韌性與市場定位的認可。"
    },
    {
      "rank": 5,
      "title": "American Electric Power (AEP) Gets Price Target Hikes from Evercore ISI and Argus",
      "publisher": "Yahoo",
      "date": "2026-03-10 17:22",
      "impact": "medium",
      "category": "分析師評級",
      "reason": "多家機構（Evercore ISI 與 Argus）同步調升目標價，強化了市場對該公司股價成長的共識。"
    },
    {
      "rank": 6,
      "title": "American Electric Power (AEP) Names Adrian Rodriguez President and COO of AEP Texas",
      "publisher": "Yahoo",
      "date": "2026-03-10 00:14",
      "impact": "low",
      "category": "高層異動",
      "reason": "任命 Adrian Rodriguez 為 AEP Texas 總裁兼營運長，有助於穩定區域業務營運與電網投資計畫的執行。"
    }
  ],
  "bearish": [
    {
      "rank": 1,
      "title": "American Electric Power: Strong Quarterly Results, But The Shares Are Fully Valued (Rating Downgrade)",
      "publisher": "SeekingAlpha",
      "date": "2026-03-08 04:36",
      "impact": "medium",
      "category": "投資評級",
      "reason": "儘管財報表現強勁，但分析師認為股價已充分反映價值，因此給予降評，提醒投資人注意估值過高的風險。"
    }
  ],
  "neutral": [
    {
      "rank": 1,
      "title": "FE or AEP: Which Is the Better Value Stock Right Now?",
      "publisher": "Zacks",
      "date": "2026-03-05 16:40",
      "impact": "low",
      "category": "市場動態",
      "reason": "此類文章為同業比較分析，旨在探討價值投資機會，並未對 AEP 本身營運產生直接影響。"
    },
    {
      "rank": 2,
      "title": "Analyst Expectations For American Electric Power's Future",
      "publisher": "Benzinga",
      "date": "2026-03-05 10:00",
      "impact": "low",
      "category": "市場動態",
      "reason": "僅為市場預期彙整，缺乏具體利多或利空訊息。"
    }
  ],
  "_schema_version": "1.1"
}