{
  "ticker": "VOO",
  "company": "S&P 500",
  "analysis_date": "2026-07-01",
  "source_file": "cache/2026-07-01/holdings/news/VOO.json",
  "summary": {
    "total_articles": 20,
    "bullish_count": 5,
    "bearish_count": 9,
    "neutral_count": 6,
    "overall_sentiment": "mixed",
    "key_theme": "市場對於 S&P 500 指數估值過高與 AI 泡沫化的擔憂，與長期投資價值及經濟韌性帶來的成長動能相互拉鋸。"
  },
  "bullish": [
    {
      "rank": 1,
      "title": "The Market Still Has Room To Climb Higher",
      "publisher": "SeekingAlpha",
      "date": "2026-06-30 09:00",
      "impact": "medium",
      "category": "市場動態",
      "reason": "分析指出美國經濟成長具有韌性，且 AI 驅動的資本支出（CAPEX）強勁，支撐 S&P 500 指數後續上漲空間。"
    },
    {
      "rank": 2,
      "title": "The Vanguard S&P 500 ETF Could Turn $200 per Month Into Over $1 Million. Here's How.",
      "publisher": "Yahoo",
      "date": "2026-06-25 11:20",
      "impact": "low",
      "category": "投資策略",
      "reason": "強調 VOO 作為核心資產的長期複利效應，吸引長期投資者持續投入資金。"
    },
    {
      "rank": 3,
      "title": "Cost Conscious? Vanguard S&P 500 ETF Tops SPDR Rival",
      "publisher": "Yahoo",
      "date": "2026-06-25 12:05",
      "impact": "low",
      "category": "產品比較",
      "reason": "VOO 的低費用率優勢使其在與 SPY 的競爭中持續勝出，有利於吸引成本敏感型投資人。"
    },
    {
      "rank": 4,
      "title": "VOO Became the First ETF to Hit $1 Trillion",
      "publisher": "Yahoo",
      "date": "2026-06-26 19:00",
      "impact": "low",
      "category": "市場動態",
      "reason": "VOO 成為史上首檔規模突破 1 兆美元的 ETF，展現其在市場中的主導地位與投資人信心。"
    },
    {
      "rank": 5,
      "title": "Inside The S&P 500's June Swoon And AI Boom, July Fireworks Possible",
      "publisher": "SeekingAlpha",
      "date": "2026-06-30 16:00",
      "impact": "low",
      "category": "市場動態",
      "reason": "提到通膨可能已觸頂，且 Fed 政策展望雖不明確但市場仍有反彈潛力。"
    }
  ],
  "bearish": [
    {
      "rank": 1,
      "title": "3 Emerging Long-Term Headwinds for the S&P 500",
      "publisher": "Yahoo",
      "date": "2026-06-29 14:50",
      "impact": "medium",
      "category": "市場動態",
      "reason": "指出長期逆風因素可能導致牛市放緩，投資人對未來報酬預期應趨於保守。"
    },
    {
      "rank": 2,
      "title": "H2 2026 S&P 500: The Bull Is Naked, And AI Must Pay",
      "publisher": "SeekingAlpha",
      "date": "2026-06-29 11:30",
      "impact": "medium",
      "category": "市場動態",
      "reason": "批評市場對 AI 的狂熱忽略了資本成本上升與未來利潤率壓縮的風險。"
    },
    {
      "rank": 3,
      "title": "Grantham Warns Of Biggest Bubble In History, Again",
      "publisher": "SeekingAlpha",
      "date": "2026-06-30 09:01",
      "impact": "medium",
      "category": "市場動態",
      "reason": "知名投資人警告市場處於歷史性泡沫中，暗示指數存在大幅修正風險。"
    },
    {
      "rank": 4,
      "title": "EQWL: S&P 500 Dashboard, Mega-Cap Bias, And Outlook",
      "publisher": "SeekingAlpha",
      "date": "2026-06-30 13:06",
      "impact": "low",
      "category": "市場動態",
      "reason": "數據顯示 S&P 500 中位數公司估值較 11 年平均高出 10%，顯示市場存在高估風險。"
    },
    {
      "rank": 5,
      "title": "My Prediction For H2 2026: Where The S&P 500 Goes From Here",
      "publisher": "SeekingAlpha",
      "date": "2026-06-29 17:30",
      "impact": "low",
      "category": "市場動態",
      "reason": "地緣政治緊張與供應鏈衝擊導致通膨壓力持續，將推升利率與市場波動率。"
    },
    {
      "rank": 6,
      "title": "The Vanguard S&P 500 ETF Is Riskier Than You Think",
      "publisher": "Yahoo",
      "date": "2026-06-30 20:56",
      "impact": "low",
      "category": "投資策略",
      "reason": "提醒投資人 VOO 的風險集中度可能高於預期，建議考慮其他多元化選項。"
    },
    {
      "rank": 7,
      "title": "Prediction: This Overlooked ETF Could Be the Smartest Buy of 2026",
      "publisher": "Yahoo",
      "date": "2026-06-30 09:33",
      "impact": "low",
      "category": "投資策略",
      "reason": "指出國際股市表現優於 S&P 500，建議投資人分散配置。"
    },
    {
      "rank": 8,
      "title": "If You Own These 10 Stocks — Analysts Think You Should Sell Them",
      "publisher": "Yahoo",
      "date": "2026-06-26 11:12",
      "impact": "low",
      "category": "市場動態",
      "reason": "分析師對 S&P 500 成分股中部分個股給予賣出評級，反映市場內部結構性隱憂。"
    }
  ],
  "neutral": [
    {
      "rank": 1,
      "title": "Is Now a Better Time to Invest in the S&P 500 or Entire Stock Market?",
      "publisher": "Yahoo",
      "date": "2026-06-29 12:50",
      "impact": "low",
      "category": "投資策略",
      "reason": "探討 S&P 500 與整體市場的重疊性，屬於投資組合配置的教學性質討論。"
    },
    {
      "rank": 2,
      "title": "VOO vs. SPY: Which Popular S&P 500 ETF Is the Better Buy?",
      "publisher": "Yahoo",
      "date": "2026-06-28 17:23",
      "impact": "low",
      "category": "產品比較",
      "reason": "比較兩大 S&P 500 ETF 的結構與費用差異，對股價無直接影響。"
    },
    {
      "rank": 3,
      "title": "Is Buying a Single S&P 500 ETF Enough for Your Portfolio?",
      "publisher": "Yahoo",
      "date": "2026-06-26 09:00",
      "impact": "low",
      "category": "投資策略",
      "reason": "關於資產配置廣度的討論，不涉及對 VOO 本身價值的看空或看多。"
    },
    {
      "rank": 4,
      "title": "Will the Vanguard S&P 500 ETF Invest in SpaceX Stock? It's Complicated.",
      "publisher": "Yahoo",
      "date": "2026-06-25 18:20",
      "impact": "low",
      "category": "市場動態",
      "reason": "討論 SpaceX 未來納入指數的可能性，屬於長期預測性質。"
    },
    {
      "rank": 5,
      "title": "My S&P 500 Prediction On Sector Outperformers And Underperformers For 2H/2026",
      "publisher": "SeekingAlpha",
      "date": "2026-06-29 17:30",
      "impact": "low",
      "category": "市場動態",
      "reason": "針對不同產業板塊的輪動預測，對整體指數影響中性。"
    },
    {
      "rank": 6,
      "title": "Going Nowhere",
      "publisher": "SeekingAlpha",
      "date": "2026-06-29 15:44",
      "impact": "low",
      "category": "市場動態",
      "reason": "描述市場短期盤整狀態，缺乏明確方向性。"
    }
  ],
  "_schema_version": "1.1"
}