{
  "marketCap": 3382075136,
  "enterpriseValue": 3009563904,
  "trailingPE": 198.26924,
  "forwardPE": 21.011827,
  "priceToSalesTrailing12Months": 3.3820415,
  "pegRatio": 3.34,
  "priceToBook": 4.027029,
  "beta": 1.533,
  "dividendYield": null,
  "trailingEps": 0.26,
  "forwardEps": 2.45338,
  "revenueGrowth": 0.322,
  "earningsGrowth": null,
  "grossMargins": 0.56831,
  "operatingMargins": 0.03404,
  "profitMargins": 0.01788,
  "totalRevenue": 1000009984,
  "freeCashflow": 117146752,
  "operatingCashflow": 134952992,
  "totalDebt": 15593000,
  "totalCash": 388104000,
  "debtToEquity": 1.815,
  "currentRatio": 4.236,
  "returnOnEquity": 0.02181,
  "returnOnAssets": 0.01313,
  "longName": "Calix, Inc.",
  "shortName": "Calix, Inc",
  "sector": "Technology",
  "industry": "Software - Infrastructure",
  "longBusinessSummary": "Calix, Inc. 及其子公司於美國、美洲其他地區、歐洲、中東、非洲及亞太地區提供雲端與軟體平台、系統及服務。該公司透過其平台與系統，協助寬頻服務供應商（BSP）提供多元化的服務。\n\n其核心產品包括：\n*   **Calix Cloud 平台**：包含 Calix Engagement Cloud、Calix Operations Cloud 及 Calix Service Cloud。該平台可配置角色導向的洞察分析，協助 BSP 透過行動應用程式（如供住戶使用的 CommandIQ 與供企業使用的 CommandWorx）預測並鎖定具備營收潛力的新服務與應用。\n*   **Calix Intelligent Access**：用於自動化與智慧化網路的存取網路解決方案。\n*   **Calix Unlimited Subscriber**：針對用戶管理服務的解決方案。\n\n此外，公司亦提供多項託管服務：\n*   **SmartLife**：包含 SmartHome 託管服務與應用，旨在提升並保障用戶居家 Wi-Fi、內容控管、網路安全、連網攝影機及社群媒體監控的連網體驗。\n*   **SmartTown**：將社區 Wi-Fi 轉型為 BSP 覆蓋範圍內無所不在、安全且受管理的體驗。\n*   **SmartBiz**：透過一體化託管服務，滿足企業主的網路連線與生產力需求。\n*   **SMARTMDU**：為各類多戶住宅提供專用且靈活的連線解決方案。\n\n同時，公司亦提供 GigaSpire 與 GigaPro 品牌的 Wi-Fi 系統，作為 BSP 為住宅及企業用戶部署完整用戶體驗解決方案的基礎。Calix, Inc. 透過直銷團隊與經銷商銷售產品。公司成立於 1999 年，總部位於加州聖荷西。",
  "recommendationMean": 1.57143,
  "company_name": "Calix, Inc.",
  "fcf_margin": 11.71,
  "net_debt": -372511000,
  "next_earnings_date": "2026-04-21",
  "fund_score": 54.0,
  "fund_score_details": {
    "rev_growth_yoy": 32.2,
    "gross_margin": 56.830999999999996,
    "fcf_margin": 11.714558241850513,
    "roic_proxy": 2.2,
    "forward_peg": 3.34,
    "debt_equity": 0.02,
    "analyst_rec": 1.57143,
    "health_score": 54.0,
    "source": "yfinance"
  },
  "_cached_at": "2026-04-21T04:18:18.126213"
}