{
  "current_price": 270.9,
  "ma50": 237.43,
  "ma200": 256.2,
  "high_52w": 303.03,
  "low_52w": 211.49,
  "avg_vol_20d": 848195,
  "current_vol": 838502,
  "change_3mo_pct": 9.35,
  "ma20": 248.65,
  "rsi14": 81.52,
  "macd": 8.995,
  "macd_signal": 6.136,
  "bb_upper": 273.33,
  "bb_lower": 223.98,
  "bb_pct": 0.95,
  "atr14": 7.39,
  "vol_ratio": 0.99,
  "trend_status": "UPTREND",
  "tech_score": 65.0,
  "var_95": -2.19,
  "sortino": 0.48,
  "max_drawdown": 30.2,
  "beta": 0.69,
  "calmar": 0.51,
  "risk_score": 58.0,
  "_cached_at": "2026-04-09T03:48:24.715139"
}