{
  "current_price": 134.39,
  "ma50": 130.03,
  "ma200": 116.97,
  "high_52w": 137.15,
  "low_52w": 96.26,
  "avg_vol_20d": 3276840,
  "current_vol": 2381400,
  "change_3mo_pct": 13.62,
  "ma20": 131.68,
  "rsi14": 71.25,
  "macd": 1.616,
  "macd_signal": 1.391,
  "bb_upper": 137.89,
  "bb_lower": 125.47,
  "bb_pct": 0.72,
  "atr14": 2.3,
  "vol_ratio": 0.73,
  "trend_status": "UPTREND",
  "tech_score": 84.0,
  "var_95": -1.54,
  "sortino": 2.3,
  "max_drawdown": 8.3,
  "beta": 0.57,
  "calmar": 3.48,
  "risk_score": 100.0,
  "_cached_at": "2026-04-16T04:16:08.829053"
}