{
  "ticker": "GOOGL",
  "company": "Google",
  "analysis_date": "2026-07-24",
  "source_file": "cache/2026-07-24/holdings/news/GOOGL.json",
  "summary": {
    "total_articles": 20,
    "bullish_count": 4,
    "bearish_count": 12,
    "neutral_count": 4,
    "overall_sentiment": "bearish",
    "key_theme": "儘管 Google Cloud 業務表現強勁，但市場對 AI 資本支出 (CapEx) 激增導致自由現金流壓力感到擔憂，加上歐盟罰款與宏觀地緣政治風險，導致股價顯著回調。"
  },
  "bullish": [
    {
      "rank": 1,
      "title": "Google Cloud CEO Kurian says customers are spending 50% more as segment blows away expectations",
      "publisher": "CNBC",
      "date": "2026-07-23 10:57",
      "impact": "high",
      "category": "財報公布",
      "reason": "Google Cloud 業務展現強勁成長動能，現有客戶支出增加 50%，顯示雲端基礎設施需求依然旺盛，為長期營收成長提供支撐。"
    },
    {
      "rank": 2,
      "title": "Alphabet's Gemini 4 Rollout, TPU Opportunity Key Catalysts to Future Upside, Morgan Stanley Says",
      "publisher": "Yahoo",
      "date": "2026-07-23 15:12",
      "impact": "medium",
      "category": "產品發布",
      "reason": "摩根士丹利指出 Gemini 4 模型與 TPU 晶片機會是未來股價上漲的關鍵催化劑，顯示分析師對其技術領先地位仍具信心。"
    },
    {
      "rank": 3,
      "title": "Dan Ives Says AI Capex Boom Continues 'Full Steam Ahead' After TSLA, GOOGL Earnings",
      "publisher": "Yahoo",
      "date": "2026-07-23 11:39",
      "impact": "medium",
      "category": "市場動態",
      "reason": "分析師 Dan Ives 強調 AI 基礎設施支出是長期趨勢，雖然短期影響利潤率，但對 AI 採用率的加速持樂觀態度。"
    },
    {
      "rank": 4,
      "title": "Alphabet Just Revealed Its Big Stake in SpaceX",
      "publisher": "Yahoo",
      "date": "2026-07-23 22:21",
      "impact": "low",
      "category": "投資組合",
      "reason": "揭露持有價值 941 億美元的 SpaceX 股份，顯示 Alphabet 在非核心資產上的潛在價值，雖對短期股價影響有限，但具備長期資產增值潛力。"
    }
  ],
  "bearish": [
    {
      "rank": 1,
      "title": "Why Alphabet (GOOGL) Shares Are Getting Obliterated Today",
      "publisher": "Yahoo",
      "date": "2026-07-23 19:08",
      "impact": "high",
      "category": "財報公布",
      "reason": "財報公布後股價單日下跌 6.5%，主要反映市場對 AI 資本支出過高導致自由現金流受壓的擔憂，此篇代表了當日市場對財報的負面情緒。"
    },
    {
      "rank": 2,
      "title": "Alphabet's Google Fined by EU Over Digital Markets Act Violations",
      "publisher": "Yahoo",
      "date": "2026-07-23 12:26",
      "impact": "medium",
      "category": "法規",
      "reason": "遭歐盟處以 8.9 億歐元 (約 10.4 億美元) 罰款，直接影響獲利能力，並凸顯監管風險持續存在。"
    },
    {
      "rank": 3,
      "title": "S&P 500, Dow, Nasdaq End Lower Over Capex Concerns, Surging Oil",
      "publisher": "Yahoo",
      "date": "2026-07-23 22:34",
      "impact": "medium",
      "category": "市場動態",
      "reason": "油價飆升至 100 美元以上引發通膨擔憂，加上科技股資本支出疑慮，導致整體市場環境惡化，對 Alphabet 股價形成壓力。"
    },
    {
      "rank": 4,
      "title": "Alphabet Lost $29 Billion on SpaceX in the Blink of an Eye",
      "publisher": "Yahoo",
      "date": "2026-07-23 20:40",
      "impact": "low",
      "category": "投資組合",
      "reason": "市場對 Alphabet 持有的 SpaceX 投資價值波動進行重新評估，雖然是帳面價值調整，但增加了投資組合的不確定性。"
    }
  ],
  "neutral": [
    {
      "rank": 1,
      "title": "Google Cloud CEO: We are very disciplined in our capex",
      "publisher": "CNBC",
      "date": "2026-07-23 11:03",
      "impact": "low",
      "category": "公司管理",
      "reason": "管理層試圖安撫市場對資本支出的擔憂，強調投資紀律，但市場反應冷淡，屬於管理層的防禦性發言。"
    },
    {
      "rank": 2,
      "title": "Warren Buffett Just Said This About Berkshire Hathaway's Massive Google Investment",
      "publisher": "Yahoo",
      "date": "2026-07-24 01:20",
      "impact": "low",
      "category": "市場動態",
      "reason": "關於巴菲特投資組合的討論，雖具市場關注度，但對 Alphabet 營運基本面無直接影響。"
    },
    {
      "rank": 3,
      "title": "Micron, SK Hynix Stocks Rise After Google Earnings. Here’s Why.",
      "publisher": "Yahoo",
      "date": "2026-07-23 20:39",
      "impact": "low",
      "category": "市場動態",
      "reason": "此新聞側重於供應鏈廠商的股價反應，反映 Alphabet 的支出對半導體產業的正面影響，對 Alphabet 本身股價無直接影響。"
    },
    {
      "rank": 4,
      "title": "Tesla's AI Bet Flounders As Alphabet's Gemini Shines",
      "publisher": "Benzinga",
      "date": "2026-07-23 10:37",
      "impact": "low",
      "category": "市場動態",
      "reason": "將 Alphabet 與 Tesla 進行比較，雖然對 Alphabet 的 AI 技術評價正面，但整體市場情緒仍受財報支出疑慮主導。"
    }
  ],
  "_schema_version": "1.1"
}